drf_nested_model_serializer/__init__.py
drf_nested_model_serializer/__init__.pyi
drf_nested_model_serializer/py.typed
drf_nested_model_serializer/serializer.py
drf_nested_model_serializer/serializer.pyi
drf_nested_model_serializer-0.0.9.dist-info/licenses/LICENSE
drf_nested_model_serializer-0.0.9.dist-info/METADATA
drf_nested_model_serializer-0.0.9.dist-info/WHEEL
drf_nested_model_serializer-0.0.9.dist-info/top_level.txt
drf_nested_model_serializer-0.0.9.dist-info/RECORD
