Metadata-Version: 2.4
Name: drf-nested-model-serializer
Version: 0.0.9
Summary: Adds support for writable nested serializers to the Django REST framework.
Author: GniLudio
License-Expression: MIT
Project-URL: Homepage, https://github.com/gniludio/drf-nested-model-serializer
Project-URL: Documentation, https://gniludio.github.io/drf-nested-model-serializer
Classifier: Programming Language :: Python :: 3
Classifier: Framework :: Django
Requires-Python: >=3.9
License-File: LICENSE
Dynamic: license-file
